algezip/__init__.py
algezip/actions.py
algezip/data.py
algezip/interactive.py
algezip/source.py
shape_warrior_t_algezip-1.0.0.dist-info/METADATA
shape_warrior_t_algezip-1.0.0.dist-info/WHEEL
shape_warrior_t_algezip-1.0.0.dist-info/entry_points.txt
shape_warrior_t_algezip-1.0.0.dist-info/RECORD
