Metadata-Version: 2.1
Name: shape-warrior-t.algezip
Version: 1.0.0
Summary: A boolean expression manipulation program that uses zippers for navigation.
Author-Email: Bonan Luan <bl.swt1@gmail.com>
License: MIT
Requires-Python: >=3.12
